cfrl/__init__.py
cfrl/agent.py
cfrl/agents/__init__.py
cfrl/agents/a3c.py
cfrl/agents/dqn.py
cfrl/agents/ppo.py
cfrl/env.py
cfrl/experiments/__init__.py
cfrl/experiments/evaluator.py
cfrl/experiments/train_agent.py
cfrl/experiments/train_agent_async.py
cfrl/nn/__init__.py
cfrl/nn/atari.py
cfrl/nn/branched.py
cfrl/nn/utils.py
cfrl/optimizers/__init__.py
cfrl/optimizers/rmsprop_eps_inside_sqrt.py
cfrl/optimizers/shared_adam.py
cfrl/optimizers/shared_rmsprop.py
cfrl/policies/__init__.py
cfrl/policies/softmax_policy.py
cfrl/utils/__init__.py
cfrl/utils/async_.py
cfrl/utils/batch_states.py
cfrl/utils/clip_l2_grad_norm.py
cfrl/utils/contexts.py
cfrl/utils/copy_param.py
cfrl/utils/mode_of_distribution.py
cfrl/utils/random_seed.py
cfrl/utils/recurrent.py
cfrl/wrappers/__init__.py
cfrl/wrappers/atari_wrappers.py
cfrl/wrappers/continuing_time_limit.py
cfrl/wrappers/monitor.py
cfrl/wrappers/render.py
cfrl-0.1.9.dist-info/WHEEL
cfrl-0.1.9.dist-info/METADATA
cfrl-0.1.9.dist-info/RECORD
